module_cli.py
module_cli-22.4.2.dist-info/entry_points.txt
module_cli-22.4.2.dist-info/LICENSE
module_cli-22.4.2.dist-info/WHEEL
module_cli-22.4.2.dist-info/METADATA
module_cli-22.4.2.dist-info/RECORD
