Metadata-Version: 2.1
Name: module-cli
Version: 22.4.2
Summary: Bootstrap extensible single-module python CLIs
Home-page: https://github.com/andrewrosss/module-cli
License: MIT
Keywords: cli,argparse,tool
Author: Andrew Ross
Author-email: andrew.ross.mail@gmail.com
Requires-Python: >=3.7,<4.0
Classifier: Environment :: Console
Classifier: Intended Audience :: Developers
Classifier: License :: OSI Approved :: MIT License
Classifier: Operating System :: OS Independent
Classifier: Programming Language :: Python :: 3
Classifier: Programming Language :: Python :: 3.0
Classifier: Programming Language :: Python :: 3.10
Classifier: Programming Language :: Python :: 3.7
Classifier: Programming Language :: Python :: 3.8
Classifier: Programming Language :: Python :: 3.9
Classifier: Topic :: Software Development :: Libraries :: Python Modules
Classifier: Topic :: Software Development :: User Interfaces
Classifier: Topic :: Utilities
Classifier: Typing :: Typed
Project-URL: Documentation, https://github.com/andrewrosss/module-cli
Project-URL: Repository, https://github.com/andrewrosss/module-cli
